Workbook

Sheet Dashboard
A1: E-COMMERCE SALES DATA DASHBOARD
A5: TOTAL REVENUE | B5: TOTAL REVENUE | C5: TOTAL REVENUE | D5: ORDERS | E5: ORDERS | F5: ORDERS | G5: UNITS SOLD | H5: UNITS SOLD | I5: UNITS SOLD | J5: AVG ORDER VALUE | K5: AVG ORDER VALUE | L5: AVG ORDER VALUE | M5: TOP CHANNEL
A6: =ROUND(Analysis!B4/100000,2) -> 10.99 | D6: =Analysis!B2 -> 300 | G6: =Analysis!B3 -> 600 | J6: =ROUND(Analysis!B6,0) -> 3664 | M6: =Analysis!B10 -> Mobile App
A9: Monthly Revenue Trend | G9: Revenue by Category
A23: Revenue by Channel | G23: Customer Segment Share

Sheet Analysis
A1: Metric | B1: Value | D1: Category | E1: Revenue (INR) | G1: Channel | H1: Revenue (INR) | J1: Segment | K1: Revenue (INR) | M1: Month | N1: Revenue (INR) | P1: State | Q1: Revenue (INR)
A2: Total Orders | B2: =COUNTA(Data!$B$2:$B$301) -> 300 | D2: Electronics | E2: =SUMIF(Data!$E$2:$E$301,D2,Data!$Q$2:$Q$301) -> 291215.24 | G2: Website | H2: =SUMIF(Data!$H$2:$H$301,G2,Data!$Q$2:$Q$301) -> 374897.9 | J2: Consumer | K2: =SUMIF(Data!$G$2:$G$301,J2,Data!$Q$2:$Q$301) -> 344939.27 | M2: Jan | N2: =SUMIFS(Data!$Q$2:$Q$301,Data!$A$2:$A$301,">="&DATE(2026,1,1),Data!$A$2:$A$301,"<"&DATE(2026,2,1)) -> 85988.9 | P2: Maharashtra | Q2: =SUMIF(Data!$C$2:$C$301,P2,Data!$Q$2:$Q$301) -> 153234.37
A3: Total Units | B3: =SUM(Data!$J$2:$J$301) -> 600 | D3: Fashion | E3: =SUMIF(Data!$E$2:$E$301,D3,Data!$Q$2:$Q$301) -> 263065.13 | G3: Mobile App | H3: =SUMIF(Data!$H$2:$H$301,G3,Data!$Q$2:$Q$301) -> 416814.64 | J3: Corporate | K3: =SUMIF(Data!$G$2:$G$301,J3,Data!$Q$2:$Q$301) -> 382197.36 | M3: Feb | N3: =SUMIFS(Data!$Q$2:$Q$301,Data!$A$2:$A$301,">="&DATE(2026,2,1),Data!$A$2:$A$301,"<"&DATE(2026,3,1)) -> 59216.07 | P3: Karnataka | Q3: =SUMIF(Data!$C$2:$C$301,P3,Data!$Q$2:$Q$301) -> 90845.94
A4: Revenue | B4: =SUM(Data!$Q$2:$Q$301) -> 1099316.7 | D4: Home | E4: =SUMIF(Data!$E$2:$E$301,D4,Data!$Q$2:$Q$301) -> 303792.3 | G4: Marketplace | H4: =SUMIF(Data!$H$2:$H$301,G4,Data!$Q$2:$Q$301) -> 307604.16 | J4: Small Business | K4: =SUMIF(Data!$G$2:$G$301,J4,Data!$Q$2:$Q$301) -> 372180.07 | M4: Mar | N4: =SUMIFS(Data!$Q$2:$Q$301,Data!$A$2:$A$301,">="&DATE(2026,3,1),Data!$A$2:$A$301,"<"&DATE(2026,4,1)) -> 115571.92 | P4: Delhi | Q4: =SUMIF(Data!$C$2:$C$301,P4,Data!$Q$2:$Q$301) -> 60611.41
A5: Profit | B5: =SUM(Data!$R$2:$R$301) -> 279962.49 | D5: Beauty | E5: =SUMIF(Data!$E$2:$E$301,D5,Data!$Q$2:$Q$301) -> 151478.97 | M5: Apr | N5: =SUMIFS(Data!$Q$2:$Q$301,Data!$A$2:$A$301,">="&DATE(2026,4,1),Data!$A$2:$A$301,"<"&DATE(2026,5,1)) -> 100951.13 | P5: Tamil Nadu | Q5: =SUMIF(Data!$C$2:$C$301,P5,Data!$Q$2:$Q$301) -> 72469.41
A6: AOV | B6: =B4/B2 -> 3664.389 | D6: Grocery | E6: =SUMIF(Data!$E$2:$E$301,D6,Data!$Q$2:$Q$301) -> 89765.06 | M6: May | N6: =SUMIFS(Data!$Q$2:$Q$301,Data!$A$2:$A$301,">="&DATE(2026,5,1),Data!$A$2:$A$301,"<"&DATE(2026,6,1)) -> 62629.28 | P6: Telangana | Q6: =SUMIF(Data!$C$2:$C$301,P6,Data!$Q$2:$Q$301) -> 98845.07
A7: Avg Rating | B7: =AVERAGE(Data!$O$2:$O$301) -> 4.28 | M7: Jun | N7: =SUMIFS(Data!$Q$2:$Q$301,Data!$A$2:$A$301,">="&DATE(2026,6,1),Data!$A$2:$A$301,"<"&DATE(2026,7,1)) -> 58905.96 | P7: Uttar Pradesh | Q7: =SUMIF(Data!$C$2:$C$301,P7,Data!$Q$2:$Q$301) -> 81998.22
A8: Avg Delivery Days | B8: =AVERAGE(Data!$N$2:$N$301) -> 3.4733333 | M8: Jul | N8: =SUMIFS(Data!$Q$2:$Q$301,Data!$A$2:$A$301,">="&DATE(2026,7,1),Data!$A$2:$A$301,"<"&DATE(2026,8,1)) -> 86224.63 | P8: Gujarat | Q8: =SUMIF(Data!$C$2:$C$301,P8,Data!$Q$2:$Q$301) -> 65452.46
A9: Top Category | B9: =INDEX(D2:D6,MATCH(MAX(E2:E6),E2:E6,0)) -> Home | M9: Aug | N9: =SUMIFS(Data!$Q$2:$Q$301,Data!$A$2:$A$301,">="&DATE(2026,8,1),Data!$A$2:$A$301,"<"&DATE(2026,9,1)) -> 114982.99 | P9: West Bengal | Q9: =SUMIF(Data!$C$2:$C$301,P9,Data!$Q$2:$Q$301) -> 120437.39
A10: Top Channel | B10: =INDEX(G2:G4,MATCH(MAX(H2:H4),H2:H4,0)) -> Mobile App | M10: Sep | N10: =SUMIFS(Data!$Q$2:$Q$301,Data!$A$2:$A$301,">="&DATE(2026,9,1),Data!$A$2:$A$301,"<"&DATE(2026,10,1)) -> 113562.92
M11: Oct | N11: =SUMIFS(Data!$Q$2:$Q$301,Data!$A$2:$A$301,">="&DATE(2026,10,1),Data!$A$2:$A$301,"<"&DATE(2026,11,1)) -> 92514.73
M12: Nov | N12: =SUMIFS(Data!$Q$2:$Q$301,Data!$A$2:$A$301,">="&DATE(2026,11,1),Data!$A$2:$A$301,"<"&DATE(2026,12,1)) -> 104760.04
M13: Dec | N13: =SUMIFS(Data!$Q$2:$Q$301,Data!$A$2:$A$301,">="&DATE(2026,12,1),Data!$A$2:$A$301,"<"&DATE(2027,1,1)) -> 104008.13

Sheet Data
A1: Order Date | B1: Order ID | C1: State | D1: City | E1: Category | F1: Product | G1: Segment | H1: Channel | I1: Payment | J1: Units | K1: Unit Price (INR) | L1: Discount % | M1: Sales Rep | N1: Delivery Days | O1: Rating | P1: Gross Sales (INR) | Q1: Revenue (INR) | R1: Profit (INR)
A2: 46083 | B2: EC26-0001 | C2: Uttar Pradesh | D2: Lucknow | E2: Grocery | F2: Healthy Snacks | G2: Consumer | H2: Marketplace | I2: Wallet | J2: 2 | K2: 599 | L2: 0 | M2: Vihaan | N2: 5 | O2: 4.5 | P2: =J2*K2 -> 1198 | Q2: =P2*(1-L2) -> 1198 | R2: =Q2*(0.24+MOD(ROW(),7)*0.005) -> 299.5
A3: 46274 | B3: EC26-0002 | C3: Kerala | D3: Kochi | E3: Beauty | F3: Hair Dryer | G3: Consumer | H3: Mobile App | I3: UPI | J3: 1 | K3: 1899 | L3: 0 | M3: Anaya | N3: 1 | O3: 5 | P3: =J3*K3 -> 1899 | Q3: =P3*(1-L3) -> 1899 | R3: =Q3*(0.24+MOD(ROW(),7)*0.005) -> 484.245
A4: 46274 | B4: EC26-0003 | C4: Madhya Pradesh | D4: Indore | E4: Home | F4: Bedsheet Set | G4: Corporate | H4: Mobile App | I4: Wallet | J4: 1 | K4: 1499 | L4: 0.05 | M4: Ishita | N4: 4 | O4: 3.5 | P4: =J4*K4 -> 1499 | Q4: =P4*(1-L4) -> 1424.05 | R4: =Q4*(0.24+MOD(ROW(),7)*0.005) -> 370.253
A5: 46298 | B5: EC26-0004 | C5: Telangana | D5: Hyderabad | E5: Home | F5: Coffee Maker | G5: Small Business | H5: Marketplace | I5: Wallet | J5: 1 | K5: 4499 | L5: 0.12 | M5: Rohan | N5: 1 | O5: 4.5 | P5: =J5*K5 -> 4499 | Q5: =P5*(1-L5) -> 3959.12 | R5: =Q5*(0.24+MOD(ROW(),7)*0.005) -> 1049.1668
A6: 46209 | B6: EC26-0005 | C6: West Bengal | D6: Kolkata | E6: Beauty | F6: Face Serum | G6: Small Business | H6: Mobile App | I6: UPI | J6: 1 | K6: 799 | L6: 0.1 | M6: Vihaan | N6: 3 | O6: 5 | P6: =J6*K6 -> 799 | Q6: =P6*(1-L6) -> 719.1 | R6: =Q6*(0.24+MOD(ROW(),7)*0.005) -> 194.157
A7: 46330 | B7: EC26-0006 | C7: West Bengal | D7: Kolkata | E7: Beauty | F7: Makeup Set | G7: Small Business | H7: Mobile App | I7: Wallet | J7: 1 | K7: 1599 | L7: 0.07 | M7: Aarav | N7: 4 | O7: 5 | P7: =J7*K7 -> 1599 | Q7: =P7*(1-L7) -> 1487.07 | R7: =Q7*(0.24+MOD(ROW(),7)*0.005) -> 356.8968
A8: 46048 | B8: EC26-0007 | C8: Punjab | D8: Ludhiana | E8: Grocery | F8: Dry Fruits Pack | G8: Corporate | H8: Website | I8: COD | J8: 2 | K8: 999 | L8: 0.07 | M8: Meera | N8: 5 | O8: 3.5 | P8: =J8*K8 -> 1998 | Q8: =P8*(1-L8) -> 1858.14 | R8: =Q8*(0.24+MOD(ROW(),7)*0.005) -> 455.2443
A9: 46381 | B9: EC26-0008 | C9: West Bengal | D9: Kolkata | E9: Beauty | F9: Makeup Set | G9: Small Business | H9: Mobile App | I9: Wallet | J9: 1 | K9: 1599 | L9: 0.07 | M9: Anaya | N9: 5 | O9: 4 | P9: =J9*K9 -> 1599 | Q9: =P9*(1-L9) -> 1487.07 | R9: =Q9*(0.24+MOD(ROW(),7)*0.005) -> 371.7675
A10: 46126 | B10: EC26-0009 | C10: Telangana | D10: Hyderabad | E10: Home | F10: Air Fryer | G10: Small Business | H10: Mobile App | I10: Wallet | J10: 1 | K10: 5999 | L10: 0.12 | M10: Anaya | N10: 3 | O10: 4 | P10: =J10*K10 -> 5999 | Q10: =P10*(1-L10) -> 5279.12 | R10: =Q10*(0.24+MOD(ROW(),7)*0.005) -> 1346.1756
A11: 46377 | B11: EC26-0010 | C11: West Bengal | D11: Kolkata | E11: Beauty | F11: Makeup Set | G11: Corporate | H11: Marketplace | I11: UPI | J11: 3 | K11: 1599 | L11: 0.07 | M11: Rohan | N11: 3 | O11: 5 | P11: =J11*K11 -> 4797 | Q11: =P11*(1-L11) -> 4461.21 | R11: =Q11*(0.24+MOD(ROW(),7)*0.005) -> 1159.9146
A12: 46073 | B12: EC26-0011 | C12: West Bengal | D12: Kolkata | E12: Grocery | F12: Green Tea | G12: Corporate | H12: Marketplace | I12: COD | J12: 2 | K12: 499 | L12: 0.02 | M12: Ishita | N12: 4 | O12: 5 | P12: =J12*K12 -> 998 | Q12: =P12*(1-L12) -> 978.04 | R12: =Q12*(0.24+MOD(ROW(),7)*0.005) -> 259.1806
A13: 46212 | B13: EC26-0012 | C13: Karnataka | D13: Bengaluru | E13: Fashion | F13: Backpack | G13: Consumer | H13: Website | I13: COD | J13: 1 | K13: 1799 | L13: 0 | M13: Ishita | N13: 4 | O13: 4 | P13: =J13*K13 -> 1799 | Q13: =P13*(1-L13) -> 1799 | R13: =Q13*(0.24+MOD(ROW(),7)*0.005) -> 485.73
... A301: 46196 | B301: EC26-0300 | C301: Maharashtra | D301: Mumbai | E301: Home | F301: Bedsheet Set | G301: Small Business | H301: Mobile App | I301: UPI | J301: 1 | K301: 1499 | L301: 0 | M301: Meera | N301: 2 | O301: 4.5 | P301: =J301*K301 -> 1499 | Q301: =P301*(1-L301) -> 1499 | R301: =Q301*(0.24+MOD(ROW(),7)*0.005) -> 359.76
